synthaser/__init__.py
synthaser/classify.py
synthaser/config.py
synthaser/download.py
synthaser/extract.py
synthaser/fasta.py
synthaser/genbank.py
synthaser/grouping.py
synthaser/main.py
synthaser/models.py
synthaser/ncbi.py
synthaser/parsers.py
synthaser/plot.py
synthaser/results.py
synthaser/rpsblast.py
synthaser/rules.json
synthaser/search.py
synthaser/settings.py
synthaser/plot/d3.min.js
synthaser/plot/index.css
synthaser/plot/index.html
synthaser/plot/synthaser.js
synthaser/plot/synthaser.min.js
synthaser-1.1.22.dist-info/LICENSE
synthaser-1.1.22.dist-info/METADATA
synthaser-1.1.22.dist-info/WHEEL
synthaser-1.1.22.dist-info/entry_points.txt
synthaser-1.1.22.dist-info/top_level.txt
synthaser-1.1.22.dist-info/RECORD
