Metadata-Version: 2.1
Name: synthaser
Version: 1.1.22
Summary: Automatic prediction and classification of protein domain architectures
Home-page: https://github.com/gamcil/synthaser
Author: Cameron Gilchrist
License: MIT
Platform: UNKNOWN
Classifier: License :: OSI Approved :: MIT License
Classifier: Programming Language :: Python :: 3
Classifier: Operating System :: OS Independent
License-File: LICENSE
Requires-Dist: requests
Requires-Dist: biopython
Requires-Dist: appdirs
